crl_checker/__init__.py
crl_checker-2.0.0.dist-info/LICENSE
crl_checker-2.0.0.dist-info/METADATA
crl_checker-2.0.0.dist-info/WHEEL
crl_checker-2.0.0.dist-info/RECORD
