Metadata-Version: 2.1
Name: crl-checker
Version: 2.0.0
Summary: Check if certificate is revoked using the x509 CRL extension
Home-page: https://github.com/fulder/crl-checker
License: MIT
Author: Michal Sadowski
Author-email: misad90@gmail.com
Requires-Python: >=3.8.1,<4.0.0
Classifier: Development Status :: 5 - Production/Stable
Classifier: Intended Audience :: Developers
Classifier: License :: OSI Approved :: MIT License
Classifier: Operating System :: OS Independent
Classifier: Programming Language :: Python :: 3
Classifier: Programming Language :: Python :: 3.9
Classifier: Programming Language :: Python :: 3.10
Classifier: Programming Language :: Python :: 3.11
Classifier: Programming Language :: Python :: 3.12
Classifier: Programming Language :: Python :: 3.8
Classifier: Topic :: Security :: Cryptography
Requires-Dist: pki-tools (>=0.0.31,<0.0.32)
Project-URL: Bug Tracker, https://github.com/fulder/crl-checker/issues
Project-URL: Repository, https://github.com/fulder/crl-checker
